dkfileutils/__init__.py
dkfileutils/changed.py
dkfileutils/listfiles.py
dkfileutils/path.py
dkfileutils/pfind.py
dkfileutils/which.py
dkfileutils-1.4.7.dist-info/LICENSE
dkfileutils-1.4.7.dist-info/METADATA
dkfileutils-1.4.7.dist-info/WHEEL
dkfileutils-1.4.7.dist-info/top_level.txt
dkfileutils-1.4.7.dist-info/RECORD
