Metadata-Version: 2.1
Name: dkfileutils
Version: 1.4.7
Summary: dkfileutils - file and directory utilities
Home-page: https://github.com/datakortet/dkfileutils/
Author: Bjorn Pettersen
Author-email: bp@datakortet.no
Classifier: Development Status :: 5 - Production/Stable
Classifier: Intended Audience :: Developers
Classifier: Programming Language :: Python :: 3
Classifier: Topic :: Software Development :: Libraries
License-File: LICENSE
